scf/__init__.py
scf/__main__.py
scf/_version.py
scf/cli.py
scf/config.py
scf/models.py
scf/server.py
scf/settings.toml
scf/suse.py
scf/utils.py
python_scf-0.4.1.dist-info/LICENSE
python_scf-0.4.1.dist-info/METADATA
python_scf-0.4.1.dist-info/WHEEL
python_scf-0.4.1.dist-info/entry_points.txt
python_scf-0.4.1.dist-info/top_level.txt
python_scf-0.4.1.dist-info/RECORD
