Metadata-Version: 2.1
Name: python-scf
Version: 0.4.1
Summary: A small tool to fetch informations about CVE from suse.com.
Author: dadav
Author-email: dadav@protonmail.com
Maintainer: dadav
Maintainer-email: dadav@protonmail.com
License: GPL
Project-URL: Bug Tracker, https://github.com/dadav/scf/issues
Project-URL: Documentation, https://scf.readthedocs.io/en/stable/
Project-URL: Source, https://github.com/dadav/scf
Keywords: suse,cve,security,cli
Classifier: License :: OSI Approved :: GNU General Public License v3 (GPLv3)
Classifier: Topic :: Software Development :: Libraries :: Python Modules
Classifier: Programming Language :: Python :: 3 :: Only
Classifier: Programming Language :: Python :: 3.7
Classifier: Programming Language :: Python :: 3.8
Classifier: Programming Language :: Python :: 3.9
Classifier: Programming Language :: Python :: 3.10
Classifier: Topic :: Utilities
Requires-Python: <4,>=3.7
License-File: LICENSE
Requires-Dist: requests
Requires-Dist: requests-cache
Requires-Dist: beautifulsoup4
Requires-Dist: fastapi
Requires-Dist: pydantic
Requires-Dist: python-dotenv
Requires-Dist: typer
Requires-Dist: uvicorn[standard]
Requires-Dist: rich
Requires-Dist: dynaconf
Requires-Dist: toml
